cursoMlet/__init__.py
cursoMlet/core.py
cursomlet_package-1.0.0.dist-info/METADATA
cursomlet_package-1.0.0.dist-info/WHEEL
cursomlet_package-1.0.0.dist-info/top_level.txt
cursomlet_package-1.0.0.dist-info/RECORD
