Metadata-Version: 2.1
Name: cursomlet-package
Version: 1.0.0
Summary: Um exemplo simples de biblioteca - curso Fiap Mlet
Home-page: https://github.com/arfmatta/cursoMlet
Author: Artur Mata
Author-email: arturrogerio@gmail.com
License: MIT
Platform: UNKNOWN
